urlcrafter/__init__.py
urlcrafter/url.py
urlcrafter-0.1.5.dist-info/licenses/LICENSE
urlcrafter-0.1.5.dist-info/METADATA
urlcrafter-0.1.5.dist-info/WHEEL
urlcrafter-0.1.5.dist-info/top_level.txt
urlcrafter-0.1.5.dist-info/RECORD
