Metadata-Version: 2.4
Name: urlcrafter
Version: 0.1.5
Summary: 🎯 Your friendly URL wizard - Craft, manipulate, and manage URLs with style!
Home-page: https://github.com/Madhav1716/URLCrafter
Author: Madhav Panchal
Author-email: madhavpanchal1716@gmail.com
Project-URL: Documentation, https://urlcrafter.readthedocs.io/
Project-URL: Source, https://github.com/Madhav1716/URLCrafter
Project-URL: Bug Tracker, https://github.com/Madhav1716/URLCrafter/issues
Keywords: url,http,api,rest,web,urlbuilder,parsing,url-manipulation,url-construction
Classifier: Development Status :: 4 - Beta
Classifier: Intended Audience :: Developers
Classifier: Topic :: Internet :: WWW/HTTP
Classifier: Topic :: Software Development :: Libraries :: Python Modules
Classifier: Programming Language :: Python :: 3
Classifier: Programming Language :: Python :: 3.7
Classifier: Programming Language :: Python :: 3.8
Classifier: Programming Language :: Python :: 3.9
Classifier: Programming Language :: Python :: 3.10
Classifier: License :: OSI Approved :: MIT License
Classifier: Operating System :: OS Independent
Requires-Python: >=3.7
License-File: LICENSE
Dynamic: author
Dynamic: author-email
Dynamic: classifier
Dynamic: description
Dynamic: description-content-type
Dynamic: home-page
Dynamic: keywords
Dynamic: license-file
Dynamic: project-url
Dynamic: requires-python
Dynamic: summary
